LICENSE
MANIFEST.in
README.md
setup.py
sentry_kavenegar/__init__.py
sentry_kavenegar/models.py
sentry_kavenegar.egg-info/PKG-INFO
sentry_kavenegar.egg-info/SOURCES.txt
sentry_kavenegar.egg-info/dependency_links.txt
sentry_kavenegar.egg-info/entry_points.txt
sentry_kavenegar.egg-info/not-zip-safe
sentry_kavenegar.egg-info/requires.txt
sentry_kavenegar.egg-info/top_level.txt