Metadata-Version: 2.1
Name: sentry-kavenegar
Version: 0.1.1
Summary: A plugin for Sentry which sends SMS notifications via Kaveneger
Home-page: https://github.com/amirasaran/sentry-kavenegar
Author: Amir Asaran
Author-email: admin@mihanmail.com
License: BSD
Platform: UNKNOWN
Classifier: Framework :: Django
Classifier: Intended Audience :: Developers
Classifier: Intended Audience :: System Administrators
Classifier: Operating System :: OS Independent
Classifier: Topic :: Software Development
